rnl/__init__.py
rnl/agents/__init__.py
rnl/agents/evaluate.py
rnl/agents/evaluator.py
rnl/configs/__init__.py
rnl/configs/config.py
rnl/configs/rewards.py
rnl/engine/__init__.py
rnl/engine/collisions.py
rnl/engine/filter.py
rnl/engine/lidar.py
rnl/engine/polygons.py
rnl/engine/spawn.py
rnl/engine/utils.py
rnl/engine/vector.py
rnl/engine/world.py
rnl/environment/__init__.py
rnl/environment/env.py
rnl/environment/generate.py
rnl/environment/robot.py
rnl/environment/sensor.py
rnl/network/__init__.py
rnl/network/model.py
rnl/network/policy.py
rnl/training/__init__.py
rnl/training/callback.py
rnl/training/interface.py
rnl/training/learn.py
rnl/training/train.py
rnl/training/utils.py
rnl-1.1.1.dist-info/METADATA
rnl-1.1.1.dist-info/WHEEL
rnl-1.1.1.dist-info/licenses/LICENSE
rnl-1.1.1.dist-info/RECORD
