Metadata-Version: 2.4
Name: rnl
Version: 1.1.1
Summary: RNL - Robot Navigation Learning
Author-email: Nicolasalan <grottimeireles@gmail.com>
License: MIT License
License-File: LICENSE
Requires-Python: <4.0,>=3.10
Requires-Dist: backoff>=2.2.1
Requires-Dist: google-api-core>=2.24.2
Requires-Dist: google-genai>=1.3.0
Requires-Dist: gymnasium<0.30.0,>=0.28.1
Requires-Dist: matplotlib>=3.3
Requires-Dist: numba<0.61.0,>=0.59.1
Requires-Dist: numpy>=1.26.4
Requires-Dist: pymunk>=6.11.1
Requires-Dist: shapely<3.0,>=1.8
Requires-Dist: stable-baselines3<3.0.0,>=2.4.1
Requires-Dist: torch>=2.5.1
Requires-Dist: tqdm>=4.67.1
Requires-Dist: wandb==0.17.6
